Workbook
Name TaxStart: Settings!$B$5
Name TaxEnd: Settings!$B$6
Name PA: Settings!$B$7
Name TaperStart: Settings!$B$8
Name BasicBand: Settings!$B$9
Name AddlThreshold: Settings!$B$10
Name BasicRate: Settings!$B$11
Name HigherRate: Settings!$B$12
Name AddlRate: Settings!$B$13
Name NICLower: Settings!$B$14
Name NICUpper: Settings!$B$15
Name NICMain: Settings!$B$16
Name NICUpperRate: Settings!$B$17
Name TradingAllow: Settings!$B$18

Sheet Start Here
A1: UK Sole Trader Tax Tracker
A2: Income & expenses log, quarterly (MTD) summaries and a tax estimate - Excel & Google Sheets
A4: How to use
A5: 1. Go to Settings and check the tax year start date (default 6 April 2026 - 5 April 2027).
A6: 2. Log every payment you receive on the Income sheet (yellow cells only).
A7: 3. Log every business cost on the Expenses sheet and pick a category from the drop-down.
A8: 4. The Quarterly Summary sheet totals income and expenses per quarter - use these figures for your MTD quarterly updates.
A9: 5. The Tax Estimate sheet shows an approximate Income Tax + Class 4 NIC bill for the year.
A11: Important notes
A12: - Quarters follow the standard tax-year periods: 6 Apr-5 Jul, 6 Jul-5 Oct, 6 Oct-5 Jan, 6 Jan-5 Apr.
A13: - The estimate assumes your only income is this self-employment, and uses England/Wales/Northern Ireland rates. Scottish rates differ.
A14: - It is an ESTIMATE to help you plan, not tax advice. Check figures against GOV.UK or an accountant before filing.
... A17: - Yellow cells = you type here. Everything else is calculated; please don't overwrite it.

Sheet Settings
A1: Settings
A2: Change the yellow cells only if the tax year or rules change
A4: Setting | B4: Value | D4: Expense categories
A5: Tax year start | B5: 46118 | D5: Cost of goods bought for resale
A6: Tax year end | B6: =DATE(YEAR(TaxStart)+1,4,5) | D6: Subcontractors / staff costs
A7: Personal allowance | B7: 12570 | D7: Car, van & travel
A8: Allowance taper starts at income of | B8: 100000 | D8: Premises & utilities
A9: Basic rate band (taxable income) | B9: 37700 | D9: Office, phone & software
A10: Additional rate threshold (taxable income) | B10: 125140 | D10: Advertising & marketing
A11: Basic rate | B11: 0.2 | D11: Bank & finance charges
A12: Higher rate | B12: 0.4 | D12: Professional fees (accountant etc.)
A13: Additional rate | B13: 0.45 | D13: Training & subscriptions
A14: Class 4 NIC lower profits limit | B14: 12570 | D14: Insurance
A15: Class 4 NIC upper profits limit | B15: 50270 | D15: Other allowable expenses
A16: Class 4 NIC main rate | B16: 0.06
A17: Class 4 NIC rate above upper limit | B17: 0.02
A18: Trading allowance (alternative to claiming expenses) | B18: 1000

Sheet Income
A1: Income
A2: Money received from customers (before any expenses)
A4: Date | B4: Customer | C4: Description | D4: Amount (£) | E4: Quarter
A5: 46132 | B5: Acme Ltd | C5: Website design | D5: 1500 | E5: =IF(A5="","",IF(OR(A5<TaxStart,A5>TaxEnd),"Outside tax year",IF(A5<DATE(YEAR(TaxStart),7,6),"Q1",IF(A5<DATE(YEAR(TaxStart),10,6),"Q2",IF(A5<DATE(YEAR(TaxStart)+1,1,6),"Q3","Q4")))))
A6: 46203 | B6: Bloom Cafe | C6: Logo | D6: 800 | E6: =IF(A6="","",IF(OR(A6<TaxStart,A6>TaxEnd),"Outside tax year",IF(A6<DATE(YEAR(TaxStart),7,6),"Q1",IF(A6<DATE(YEAR(TaxStart),10,6),"Q2",IF(A6<DATE(YEAR(TaxStart)+1,1,6),"Q3","Q4")))))
A7: 46209 | B7: Acme Ltd | C7: Maintenance | D7: 600 | E7: =IF(A7="","",IF(OR(A7<TaxStart,A7>TaxEnd),"Outside tax year",IF(A7<DATE(YEAR(TaxStart),7,6),"Q1",IF(A7<DATE(YEAR(TaxStart),10,6),"Q2",IF(A7<DATE(YEAR(TaxStart)+1,1,6),"Q3","Q4")))))
A8: 46300 | B8: J Smith | C8: Consulting | D8: 2500 | E8: =IF(A8="","",IF(OR(A8<TaxStart,A8>TaxEnd),"Outside tax year",IF(A8<DATE(YEAR(TaxStart),7,6),"Q1",IF(A8<DATE(YEAR(TaxStart),10,6),"Q2",IF(A8<DATE(YEAR(TaxStart)+1,1,6),"Q3","Q4")))))
A9: 46301 | B9: Bloom Cafe | C9: Menu design | D9: 1200 | E9: =IF(A9="","",IF(OR(A9<TaxStart,A9>TaxEnd),"Outside tax year",IF(A9<DATE(YEAR(TaxStart),7,6),"Q1",IF(A9<DATE(YEAR(TaxStart),10,6),"Q2",IF(A9<DATE(YEAR(TaxStart)+1,1,6),"Q3","Q4")))))
A10: 46392 | B10: Acme Ltd | C10: Retainer | D10: 3000 | E10: =IF(A10="","",IF(OR(A10<TaxStart,A10>TaxEnd),"Outside tax year",IF(A10<DATE(YEAR(TaxStart),7,6),"Q1",IF(A10<DATE(YEAR(TaxStart),10,6),"Q2",IF(A10<DATE(YEAR(TaxStart)+1,1,6),"Q3","Q4")))))
A11: 46393 | B11: Acme Ltd | C11: Retainer | D11: 3000 | E11: =IF(A11="","",IF(OR(A11<TaxStart,A11>TaxEnd),"Outside tax year",IF(A11<DATE(YEAR(TaxStart),7,6),"Q1",IF(A11<DATE(YEAR(TaxStart),10,6),"Q2",IF(A11<DATE(YEAR(TaxStart)+1,1,6),"Q3","Q4")))))
A12: 46477 | B12: J Smith | C12: Project | D12: 8000 | E12: =IF(A12="","",IF(OR(A12<TaxStart,A12>TaxEnd),"Outside tax year",IF(A12<DATE(YEAR(TaxStart),7,6),"Q1",IF(A12<DATE(YEAR(TaxStart),10,6),"Q2",IF(A12<DATE(YEAR(TaxStart)+1,1,6),"Q3","Q4")))))
A13: 46483 | B13: Late Co | C13: Next year job | D13: 999 | E13: =IF(A13="","",IF(OR(A13<TaxStart,A13>TaxEnd),"Outside tax year",IF(A13<DATE(YEAR(TaxStart),7,6),"Q1",IF(A13<DATE(YEAR(TaxStart),10,6),"Q2",IF(A13<DATE(YEAR(TaxStart)+1,1,6),"Q3","Q4")))))
E14: =IF(A14="","",IF(OR(A14<TaxStart,A14>TaxEnd),"Outside tax year",IF(A14<DATE(YEAR(TaxStart),7,6),"Q1",IF(A14<DATE(YEAR(TaxStart),10,6),"Q2",IF(A14<DATE(YEAR(TaxStart)+1,1,6),"Q3","Q4")))))
E15: =IF(A15="","",IF(OR(A15<TaxStart,A15>TaxEnd),"Outside tax year",IF(A15<DATE(YEAR(TaxStart),7,6),"Q1",IF(A15<DATE(YEAR(TaxStart),10,6),"Q2",IF(A15<DATE(YEAR(TaxStart)+1,1,6),"Q3","Q4")))))
E16: =IF(A16="","",IF(OR(A16<TaxStart,A16>TaxEnd),"Outside tax year",IF(A16<DATE(YEAR(TaxStart),7,6),"Q1",IF(A16<DATE(YEAR(TaxStart),10,6),"Q2",IF(A16<DATE(YEAR(TaxStart)+1,1,6),"Q3","Q4")))))
E17: =IF(A17="","",IF(OR(A17<TaxStart,A17>TaxEnd),"Outside tax year",IF(A17<DATE(YEAR(TaxStart),7,6),"Q1",IF(A17<DATE(YEAR(TaxStart),10,6),"Q2",IF(A17<DATE(YEAR(TaxStart)+1,1,6),"Q3","Q4")))))
E18: =IF(A18="","",IF(OR(A18<TaxStart,A18>TaxEnd),"Outside tax year",IF(A18<DATE(YEAR(TaxStart),7,6),"Q1",IF(A18<DATE(YEAR(TaxStart),10,6),"Q2",IF(A18<DATE(YEAR(TaxStart)+1,1,6),"Q3","Q4")))))
E19: =IF(A19="","",IF(OR(A19<TaxStart,A19>TaxEnd),"Outside tax year",IF(A19<DATE(YEAR(TaxStart),7,6),"Q1",IF(A19<DATE(YEAR(TaxStart),10,6),"Q2",IF(A19<DATE(YEAR(TaxStart)+1,1,6),"Q3","Q4")))))
E20: =IF(A20="","",IF(OR(A20<TaxStart,A20>TaxEnd),"Outside tax year",IF(A20<DATE(YEAR(TaxStart),7,6),"Q1",IF(A20<DATE(YEAR(TaxStart),10,6),"Q2",IF(A20<DATE(YEAR(TaxStart)+1,1,6),"Q3","Q4")))))
E21: =IF(A21="","",IF(OR(A21<TaxStart,A21>TaxEnd),"Outside tax year",IF(A21<DATE(YEAR(TaxStart),7,6),"Q1",IF(A21<DATE(YEAR(TaxStart),10,6),"Q2",IF(A21<DATE(YEAR(TaxStart)+1,1,6),"Q3","Q4")))))
E22: =IF(A22="","",IF(OR(A22<TaxStart,A22>TaxEnd),"Outside tax year",IF(A22<DATE(YEAR(TaxStart),7,6),"Q1",IF(A22<DATE(YEAR(TaxStart),10,6),"Q2",IF(A22<DATE(YEAR(TaxStart)+1,1,6),"Q3","Q4")))))
E23: =IF(A23="","",IF(OR(A23<TaxStart,A23>TaxEnd),"Outside tax year",IF(A23<DATE(YEAR(TaxStart),7,6),"Q1",IF(A23<DATE(YEAR(TaxStart),10,6),"Q2",IF(A23<DATE(YEAR(TaxStart)+1,1,6),"Q3","Q4")))))
E24: =IF(A24="","",IF(OR(A24<TaxStart,A24>TaxEnd),"Outside tax year",IF(A24<DATE(YEAR(TaxStart),7,6),"Q1",IF(A24<DATE(YEAR(TaxStart),10,6),"Q2",IF(A24<DATE(YEAR(TaxStart)+1,1,6),"Q3","Q4")))))
E25: =IF(A25="","",IF(OR(A25<TaxStart,A25>TaxEnd),"Outside tax year",IF(A25<DATE(YEAR(TaxStart),7,6),"Q1",IF(A25<DATE(YEAR(TaxStart),10,6),"Q2",IF(A25<DATE(YEAR(TaxStart)+1,1,6),"Q3","Q4")))))
... E1004: =IF(A1004="","",IF(OR(A1004<TaxStart,A1004>TaxEnd),"Outside tax year",IF(A1004<DATE(YEAR(TaxStart),7,6),"Q1",IF(A1004<DATE(YEAR(TaxStart),10,6),"Q2",IF(A1004<DATE(YEAR(TaxStart)+1,1,6),"Q3","Q4")))))

Sheet Expenses
A1: Expenses
A2: Allowable business costs - pick a category from the drop-down
A4: Date | B4: Supplier | C4: Description | D4: Category | E4: Amount (£) | F4: Quarter
A5: 46143 | B5: Adobe | C5: Subscription | D5: Office, phone & software | E5: 200 | F5: =IF(A5="","",IF(OR(A5<TaxStart,A5>TaxEnd),"Outside tax year",IF(A5<DATE(YEAR(TaxStart),7,6),"Q1",IF(A5<DATE(YEAR(TaxStart),10,6),"Q2",IF(A5<DATE(YEAR(TaxStart)+1,1,6),"Q3","Q4")))))
A6: 46235 | B6: Google | C6: Ads | D6: Advertising & marketing | E6: 300 | F6: =IF(A6="","",IF(OR(A6<TaxStart,A6>TaxEnd),"Outside tax year",IF(A6<DATE(YEAR(TaxStart),7,6),"Q1",IF(A6<DATE(YEAR(TaxStart),10,6),"Q2",IF(A6<DATE(YEAR(TaxStart)+1,1,6),"Q3","Q4")))))
A7: 46327 | B7: Train Co | C7: Travel | D7: Car, van & travel | E7: 150 | F7: =IF(A7="","",IF(OR(A7<TaxStart,A7>TaxEnd),"Outside tax year",IF(A7<DATE(YEAR(TaxStart),7,6),"Q1",IF(A7<DATE(YEAR(TaxStart),10,6),"Q2",IF(A7<DATE(YEAR(TaxStart)+1,1,6),"Q3","Q4")))))
A8: 46419 | B8: Accountant | C8: Fees | D8: Professional fees (accountant etc.) | E8: 350 | F8: =IF(A8="","",IF(OR(A8<TaxStart,A8>TaxEnd),"Outside tax year",IF(A8<DATE(YEAR(TaxStart),7,6),"Q1",IF(A8<DATE(YEAR(TaxStart),10,6),"Q2",IF(A8<DATE(YEAR(TaxStart)+1,1,6),"Q3","Q4")))))
F9: =IF(A9="","",IF(OR(A9<TaxStart,A9>TaxEnd),"Outside tax year",IF(A9<DATE(YEAR(TaxStart),7,6),"Q1",IF(A9<DATE(YEAR(TaxStart),10,6),"Q2",IF(A9<DATE(YEAR(TaxStart)+1,1,6),"Q3","Q4")))))
F10: =IF(A10="","",IF(OR(A10<TaxStart,A10>TaxEnd),"Outside tax year",IF(A10<DATE(YEAR(TaxStart),7,6),"Q1",IF(A10<DATE(YEAR(TaxStart),10,6),"Q2",IF(A10<DATE(YEAR(TaxStart)+1,1,6),"Q3","Q4")))))
F11: =IF(A11="","",IF(OR(A11<TaxStart,A11>TaxEnd),"Outside tax year",IF(A11<DATE(YEAR(TaxStart),7,6),"Q1",IF(A11<DATE(YEAR(TaxStart),10,6),"Q2",IF(A11<DATE(YEAR(TaxStart)+1,1,6),"Q3","Q4")))))
F12: =IF(A12="","",IF(OR(A12<TaxStart,A12>TaxEnd),"Outside tax year",IF(A12<DATE(YEAR(TaxStart),7,6),"Q1",IF(A12<DATE(YEAR(TaxStart),10,6),"Q2",IF(A12<DATE(YEAR(TaxStart)+1,1,6),"Q3","Q4")))))
F13: =IF(A13="","",IF(OR(A13<TaxStart,A13>TaxEnd),"Outside tax year",IF(A13<DATE(YEAR(TaxStart),7,6),"Q1",IF(A13<DATE(YEAR(TaxStart),10,6),"Q2",IF(A13<DATE(YEAR(TaxStart)+1,1,6),"Q3","Q4")))))
F14: =IF(A14="","",IF(OR(A14<TaxStart,A14>TaxEnd),"Outside tax year",IF(A14<DATE(YEAR(TaxStart),7,6),"Q1",IF(A14<DATE(YEAR(TaxStart),10,6),"Q2",IF(A14<DATE(YEAR(TaxStart)+1,1,6),"Q3","Q4")))))
F15: =IF(A15="","",IF(OR(A15<TaxStart,A15>TaxEnd),"Outside tax year",IF(A15<DATE(YEAR(TaxStart),7,6),"Q1",IF(A15<DATE(YEAR(TaxStart),10,6),"Q2",IF(A15<DATE(YEAR(TaxStart)+1,1,6),"Q3","Q4")))))
F16: =IF(A16="","",IF(OR(A16<TaxStart,A16>TaxEnd),"Outside tax year",IF(A16<DATE(YEAR(TaxStart),7,6),"Q1",IF(A16<DATE(YEAR(TaxStart),10,6),"Q2",IF(A16<DATE(YEAR(TaxStart)+1,1,6),"Q3","Q4")))))
F17: =IF(A17="","",IF(OR(A17<TaxStart,A17>TaxEnd),"Outside tax year",IF(A17<DATE(YEAR(TaxStart),7,6),"Q1",IF(A17<DATE(YEAR(TaxStart),10,6),"Q2",IF(A17<DATE(YEAR(TaxStart)+1,1,6),"Q3","Q4")))))
F18: =IF(A18="","",IF(OR(A18<TaxStart,A18>TaxEnd),"Outside tax year",IF(A18<DATE(YEAR(TaxStart),7,6),"Q1",IF(A18<DATE(YEAR(TaxStart),10,6),"Q2",IF(A18<DATE(YEAR(TaxStart)+1,1,6),"Q3","Q4")))))
F19: =IF(A19="","",IF(OR(A19<TaxStart,A19>TaxEnd),"Outside tax year",IF(A19<DATE(YEAR(TaxStart),7,6),"Q1",IF(A19<DATE(YEAR(TaxStart),10,6),"Q2",IF(A19<DATE(YEAR(TaxStart)+1,1,6),"Q3","Q4")))))
F20: =IF(A20="","",IF(OR(A20<TaxStart,A20>TaxEnd),"Outside tax year",IF(A20<DATE(YEAR(TaxStart),7,6),"Q1",IF(A20<DATE(YEAR(TaxStart),10,6),"Q2",IF(A20<DATE(YEAR(TaxStart)+1,1,6),"Q3","Q4")))))
... F1004: =IF(A1004="","",IF(OR(A1004<TaxStart,A1004>TaxEnd),"Outside tax year",IF(A1004<DATE(YEAR(TaxStart),7,6),"Q1",IF(A1004<DATE(YEAR(TaxStart),10,6),"Q2",IF(A1004<DATE(YEAR(TaxStart)+1,1,6),"Q3","Q4")))))

Sheet Quarterly Summary
A1: Quarterly Summary (MTD)
A2: Use these totals for your quarterly updates
B4: Q1 | C4: Q2 | D4: Q3 | E4: Q4 | F4: Full year
A5: Period | B5: =TEXT(TaxStart,"d mmm yy")&" - "&TEXT(DATE(YEAR(TaxStart),7,5),"d mmm yy") | C5: =TEXT(DATE(YEAR(TaxStart),7,6),"d mmm yy")&" - "&TEXT(DATE(YEAR(TaxStart),10,5),"d mmm yy") | D5: =TEXT(DATE(YEAR(TaxStart),10,6),"d mmm yy")&" - "&TEXT(DATE(YEAR(TaxStart)+1,1,5),"d mmm yy") | E5: =TEXT(DATE(YEAR(TaxStart)+1,1,6),"d mmm yy")&" - "&TEXT(TaxEnd,"d mmm yy") | F5: =TEXT(TaxStart,"d mmm yy")&" - "&TEXT(TaxEnd,"d mmm yy")
A6: Total income | B6: =SUMIFS(Income!$D$5:$D$1004,Income!$E$5:$E$1004,B$4) | C6: =SUMIFS(Income!$D$5:$D$1004,Income!$E$5:$E$1004,C$4) | D6: =SUMIFS(Income!$D$5:$D$1004,Income!$E$5:$E$1004,D$4) | E6: =SUMIFS(Income!$D$5:$D$1004,Income!$E$5:$E$1004,E$4) | F6: =SUM(B6:E6)
A8: Expenses by category
A9: =Settings!D5 | B9: =SUMIFS(Expenses!$E$5:$E$1004,Expenses!$D$5:$D$1004,$A9,Expenses!$F$5:$F$1004,B$4) | C9: =SUMIFS(Expenses!$E$5:$E$1004,Expenses!$D$5:$D$1004,$A9,Expenses!$F$5:$F$1004,C$4) | D9: =SUMIFS(Expenses!$E$5:$E$1004,Expenses!$D$5:$D$1004,$A9,Expenses!$F$5:$F$1004,D$4) | E9: =SUMIFS(Expenses!$E$5:$E$1004,Expenses!$D$5:$D$1004,$A9,Expenses!$F$5:$F$1004,E$4) | F9: =SUM(B9:E9)
A10: =Settings!D6 | B10: =SUMIFS(Expenses!$E$5:$E$1004,Expenses!$D$5:$D$1004,$A10,Expenses!$F$5:$F$1004,B$4) | C10: =SUMIFS(Expenses!$E$5:$E$1004,Expenses!$D$5:$D$1004,$A10,Expenses!$F$5:$F$1004,C$4) | D10: =SUMIFS(Expenses!$E$5:$E$1004,Expenses!$D$5:$D$1004,$A10,Expenses!$F$5:$F$1004,D$4) | E10: =SUMIFS(Expenses!$E$5:$E$1004,Expenses!$D$5:$D$1004,$A10,Expenses!$F$5:$F$1004,E$4) | F10: =SUM(B10:E10)
A11: =Settings!D7 | B11: =SUMIFS(Expenses!$E$5:$E$1004,Expenses!$D$5:$D$1004,$A11,Expenses!$F$5:$F$1004,B$4) | C11: =SUMIFS(Expenses!$E$5:$E$1004,Expenses!$D$5:$D$1004,$A11,Expenses!$F$5:$F$1004,C$4) | D11: =SUMIFS(Expenses!$E$5:$E$1004,Expenses!$D$5:$D$1004,$A11,Expenses!$F$5:$F$1004,D$4) | E11: =SUMIFS(Expenses!$E$5:$E$1004,Expenses!$D$5:$D$1004,$A11,Expenses!$F$5:$F$1004,E$4) | F11: =SUM(B11:E11)
A12: =Settings!D8 | B12: =SUMIFS(Expenses!$E$5:$E$1004,Expenses!$D$5:$D$1004,$A12,Expenses!$F$5:$F$1004,B$4) | C12: =SUMIFS(Expenses!$E$5:$E$1004,Expenses!$D$5:$D$1004,$A12,Expenses!$F$5:$F$1004,C$4) | D12: =SUMIFS(Expenses!$E$5:$E$1004,Expenses!$D$5:$D$1004,$A12,Expenses!$F$5:$F$1004,D$4) | E12: =SUMIFS(Expenses!$E$5:$E$1004,Expenses!$D$5:$D$1004,$A12,Expenses!$F$5:$F$1004,E$4) | F12: =SUM(B12:E12)
A13: =Settings!D9 | B13: =SUMIFS(Expenses!$E$5:$E$1004,Expenses!$D$5:$D$1004,$A13,Expenses!$F$5:$F$1004,B$4) | C13: =SUMIFS(Expenses!$E$5:$E$1004,Expenses!$D$5:$D$1004,$A13,Expenses!$F$5:$F$1004,C$4) | D13: =SUMIFS(Expenses!$E$5:$E$1004,Expenses!$D$5:$D$1004,$A13,Expenses!$F$5:$F$1004,D$4) | E13: =SUMIFS(Expenses!$E$5:$E$1004,Expenses!$D$5:$D$1004,$A13,Expenses!$F$5:$F$1004,E$4) | F13: =SUM(B13:E13)
A14: =Settings!D10 | B14: =SUMIFS(Expenses!$E$5:$E$1004,Expenses!$D$5:$D$1004,$A14,Expenses!$F$5:$F$1004,B$4) | C14: =SUMIFS(Expenses!$E$5:$E$1004,Expenses!$D$5:$D$1004,$A14,Expenses!$F$5:$F$1004,C$4) | D14: =SUMIFS(Expenses!$E$5:$E$1004,Expenses!$D$5:$D$1004,$A14,Expenses!$F$5:$F$1004,D$4) | E14: =SUMIFS(Expenses!$E$5:$E$1004,Expenses!$D$5:$D$1004,$A14,Expenses!$F$5:$F$1004,E$4) | F14: =SUM(B14:E14)
A15: =Settings!D11 | B15: =SUMIFS(Expenses!$E$5:$E$1004,Expenses!$D$5:$D$1004,$A15,Expenses!$F$5:$F$1004,B$4) | C15: =SUMIFS(Expenses!$E$5:$E$1004,Expenses!$D$5:$D$1004,$A15,Expenses!$F$5:$F$1004,C$4) | D15: =SUMIFS(Expenses!$E$5:$E$1004,Expenses!$D$5:$D$1004,$A15,Expenses!$F$5:$F$1004,D$4) | E15: =SUMIFS(Expenses!$E$5:$E$1004,Expenses!$D$5:$D$1004,$A15,Expenses!$F$5:$F$1004,E$4) | F15: =SUM(B15:E15)
A16: =Settings!D12 | B16: =SUMIFS(Expenses!$E$5:$E$1004,Expenses!$D$5:$D$1004,$A16,Expenses!$F$5:$F$1004,B$4) | C16: =SUMIFS(Expenses!$E$5:$E$1004,Expenses!$D$5:$D$1004,$A16,Expenses!$F$5:$F$1004,C$4) | D16: =SUMIFS(Expenses!$E$5:$E$1004,Expenses!$D$5:$D$1004,$A16,Expenses!$F$5:$F$1004,D$4) | E16: =SUMIFS(Expenses!$E$5:$E$1004,Expenses!$D$5:$D$1004,$A16,Expenses!$F$5:$F$1004,E$4) | F16: =SUM(B16:E16)
A17: =Settings!D13 | B17: =SUMIFS(Expenses!$E$5:$E$1004,Expenses!$D$5:$D$1004,$A17,Expenses!$F$5:$F$1004,B$4) | C17: =SUMIFS(Expenses!$E$5:$E$1004,Expenses!$D$5:$D$1004,$A17,Expenses!$F$5:$F$1004,C$4) | D17: =SUMIFS(Expenses!$E$5:$E$1004,Expenses!$D$5:$D$1004,$A17,Expenses!$F$5:$F$1004,D$4) | E17: =SUMIFS(Expenses!$E$5:$E$1004,Expenses!$D$5:$D$1004,$A17,Expenses!$F$5:$F$1004,E$4) | F17: =SUM(B17:E17)
A18: =Settings!D14 | B18: =SUMIFS(Expenses!$E$5:$E$1004,Expenses!$D$5:$D$1004,$A18,Expenses!$F$5:$F$1004,B$4) | C18: =SUMIFS(Expenses!$E$5:$E$1004,Expenses!$D$5:$D$1004,$A18,Expenses!$F$5:$F$1004,C$4) | D18: =SUMIFS(Expenses!$E$5:$E$1004,Expenses!$D$5:$D$1004,$A18,Expenses!$F$5:$F$1004,D$4) | E18: =SUMIFS(Expenses!$E$5:$E$1004,Expenses!$D$5:$D$1004,$A18,Expenses!$F$5:$F$1004,E$4) | F18: =SUM(B18:E18)
A19: =Settings!D15 | B19: =SUMIFS(Expenses!$E$5:$E$1004,Expenses!$D$5:$D$1004,$A19,Expenses!$F$5:$F$1004,B$4) | C19: =SUMIFS(Expenses!$E$5:$E$1004,Expenses!$D$5:$D$1004,$A19,Expenses!$F$5:$F$1004,C$4) | D19: =SUMIFS(Expenses!$E$5:$E$1004,Expenses!$D$5:$D$1004,$A19,Expenses!$F$5:$F$1004,D$4) | E19: =SUMIFS(Expenses!$E$5:$E$1004,Expenses!$D$5:$D$1004,$A19,Expenses!$F$5:$F$1004,E$4) | F19: =SUM(B19:E19)
A20: Total expenses | B20: =SUM(B9:B19) | C20: =SUM(C9:C19) | D20: =SUM(D9:D19) | E20: =SUM(E9:E19) | F20: =SUM(F9:F19)
A22: Net profit (income - expenses) | B22: =B6-B20 | C22: =C6-C20 | D22: =D6-D20 | E22: =E6-E20 | F22: =F6-F20
A24: Check: entries dated outside the tax year (should be 0) | F24: =COUNTIF(Income!$E$5:$E$1004,"Outside tax year")+COUNTIF(Expenses!$F$5:$F$1004,"Outside tax year")

Sheet Tax Estimate
A1: Tax Estimate
A2: Approximate Income Tax + Class 4 NIC on self-employment profit (England, Wales & NI)
B4: Amount | C4: Notes
A5: Total income | B5: ='Quarterly Summary'!F6
A6: Total expenses claimed | B6: ='Quarterly Summary'!F20
A7: Deduction used | B7: =MAX(B6,MIN(B5,TradingAllow)) | C7: Higher of your expenses or the trading allowance (max £1,000)
A8: Taxable profit | B8: =MAX(0,B5-B7)
A9: Personal allowance (after taper) | B9: =MAX(0,PA-MAX(0,(B8-TaperStart)/2)) | C9: Reduces £1 for every £2 over £100,000
A10: Taxable income after allowance | B10: =MAX(0,B8-B9)
A11: Tax at basic rate | B11: =BasicRate*MIN(B10,BasicBand)
A12: Tax at higher rate | B12: =HigherRate*MAX(0,MIN(B10,AddlThreshold)-BasicBand)
A13: Tax at additional rate | B13: =AddlRate*MAX(0,B10-AddlThreshold)
A14: Income Tax | B14: =SUM(B11:B13)
A15: Class 4 NIC | B15: =IF(B8<=NICLower,0,NICMain*(MIN(B8,NICUpper)-NICLower)+NICUpperRate*MAX(0,B8-NICUpper)) | C15: Class 2 is no longer compulsory
A16: Total estimated tax + NIC | B16: =B14+B15
A17: Suggested amount to set aside each month | B17: =B16/12
A18: Effective rate on profit | B18: =IF(B8=0,0,B16/B8)
A20: Estimate only - not tax advice. Check GOV.UK or ask an accountant before filing.
